tez/__init__.py
tez/enums.py
tez/logger.py
tez/utils.py
tez/callbacks/__init__.py
tez/callbacks/callbacks.py
tez/callbacks/early_stopping.py
tez/callbacks/progress.py
tez/callbacks/tensorboard.py
tez/datasets/__init__.py
tez/datasets/generic.py
tez/datasets/image_classification.py
tez/datasets/image_segmentation.py
tez/model/__init__.py
tez/model/config.py
tez/model/model.py
tez/model/tez.py
tez-0.7.2.dist-info/LICENSE
tez-0.7.2.dist-info/METADATA
tez-0.7.2.dist-info/WHEEL
tez-0.7.2.dist-info/top_level.txt
tez-0.7.2.dist-info/RECORD
