Metadata-Version: 2.1
Name: tez
Version: 0.7.2
Summary: tez - a simple pytorch trainer
Home-page: https://github.com/abhishekkrthakur/tez
Author: Abhishek Thakur
License: Apache License
Platform: linux
Platform: unix
Requires-Python: >=3.7
License-File: LICENSE
Requires-Dist: loguru (>=0.6.0)
Requires-Dist: accelerate (>=0.12.0)
Requires-Dist: tqdm (>=4.64.0)
